pycman/__init__.py
pycman/pacman.py
pycman/simulator.py
pycman/test_pacman_log.json
pycman/test_params.json
pycman/__pycache__/__init__.cpython-35.pyc
pycman/__pycache__/__init__.cpython-36.pyc
pycman/__pycache__/pacman.cpython-35.pyc
pycman/__pycache__/simulator.cpython-35.pyc
pycman/__pycache__/test.cpython-35.pyc
pycman/sprites/diamond.png
pycman/sprites/monster.png
pycman/sprites/pacman.png
pycman/sprites/wall.png
pycman2-0.1.dist-info/DESCRIPTION.rst
pycman2-0.1.dist-info/METADATA
pycman2-0.1.dist-info/RECORD
pycman2-0.1.dist-info/WHEEL
pycman2-0.1.dist-info/metadata.json
pycman2-0.1.dist-info/top_level.txt
