Metadata-Version: 2.0
Name: pycman2
Version: 0.1
Summary: Pacman game simulator in Python
Home-page: https://github.com/reachsumit/pycman
Author: Sumit Kumar (Arora)
Author-email: sam.sumitkumar@gmail.com
License: UNKNOWN
Platform: UNKNOWN
Classifier: Programming Language :: Python :: 3
Classifier: License :: OSI Approved :: MIT License
Classifier: Operating System :: OS Independent
Requires-Dist: click
